lins_mail_sender/__init__.py
lins_mail_sender/lins_mail.py
lins_mail_sender-1.1.4.17.dist-info/METADATA
lins_mail_sender-1.1.4.17.dist-info/WHEEL
lins_mail_sender-1.1.4.17.dist-info/top_level.txt
lins_mail_sender-1.1.4.17.dist-info/RECORD
