Metadata-Version: 2.1
Name: lins-mail-sender
Version: 1.1.4.17
Summary: Pacote de envio de email
Home-page: https://bitbucket.org/grupolinsferrao/pypck-lins-mail-sender/
Author: Nicollas Neumann Borges
Author-email: nicollasborges@lojaspompeia.com.br
License: MIT
Platform: UNKNOWN
